inventario_libreria/__init__.py
inventario_libreria/builders.py
inventario_libreria/estructuras.py
inventario_libreria/factory.py
inventario_libreria/funciones.py
inventario_libreria-0.1.0.dist-info/METADATA
inventario_libreria-0.1.0.dist-info/WHEEL
inventario_libreria-0.1.0.dist-info/top_level.txt
inventario_libreria-0.1.0.dist-info/RECORD
