Metadata-Version: 2.4
Name: inventario-libreria
Version: 0.1.0
Summary: Una librería pequeña para la gestión de inventario y cálculos básicos.
Home-page: https://github.com/CelsoPaolo/Mi_libreria.git
Author: Celso Paolo Velasco Espinoza
Author-email: celsovelasco.sis24ch@tecba.edu.bo
Classifier: Programming Language :: Python :: 3
Classifier: License :: OSI Approved :: MIT License
Classifier: Operating System :: OS Independent
Requires-Python: >=3.6
Dynamic: author
Dynamic: author-email
Dynamic: classifier
Dynamic: description
Dynamic: description-content-type
Dynamic: home-page
Dynamic: requires-python
Dynamic: summary
